osmdt/__init__.py
osmdt/extract.py
osmdt/fetch.py
osmdt/process.py
osm_diff_tool-1.1.0.dist-info/LICENSE
osm_diff_tool-1.1.0.dist-info/METADATA
osm_diff_tool-1.1.0.dist-info/WHEEL
osm_diff_tool-1.1.0.dist-info/top_level.txt
osm_diff_tool-1.1.0.dist-info/RECORD
